beetsplug/bpmanalyser/__init__.py
beetsplug/bpmanalyser/analyser.py
beetsplug/bpmanalyser/command.py
beetsplug/bpmanalyser/version.py
beets_bpmanalyser-1.5.9.dist-info/LICENSE.txt
beets_bpmanalyser-1.5.9.dist-info/METADATA
beets_bpmanalyser-1.5.9.dist-info/WHEEL
beets_bpmanalyser-1.5.9.dist-info/top_level.txt
beets_bpmanalyser-1.5.9.dist-info/RECORD
