Metadata-Version: 2.1
Name: beets-bpmanalyser
Version: 1.5.9
Summary: A beets plugin for analysing tempo of songs and storing it in the bpm tag.
Home-page: https://github.com/adamjakab/BeetsPluginBpmAnalyser
Author: Adam Jakab
Author-email: adam@jakab.pro
License: MIT
Platform: ALL
Classifier: Topic :: Multimedia :: Sound/Audio
Classifier: License :: OSI Approved :: MIT License
Classifier: Environment :: Console
Classifier: Programming Language :: Python :: 3
Classifier: Programming Language :: Python :: 3.8
Classifier: Programming Language :: Python :: 3.9
Classifier: Programming Language :: Python :: 3.10
Classifier: Programming Language :: Python :: 3.11
Classifier: Programming Language :: Python :: 3.12
Requires-Python: >=3.8
License-File: LICENSE.txt
Requires-Dist: beets >=1.4.9
Requires-Dist: aubio
Requires-Dist: numpy
Requires-Dist: pydub
